clinproc/__init__.py
clinproc/ctconfig.py
clinproc/ctdocument.py
clinproc/eligibility.py
clinproc/proc.py
clinproc/regex_patterns.py
clinproc/stats.py
clinproc/utils.py
clinproc/tests/__init__.py
clinproc/tests/clinproc_tests.py
clinproc-0.2.4.dist-info/LICENSE
clinproc-0.2.4.dist-info/METADATA
clinproc-0.2.4.dist-info/WHEEL
clinproc-0.2.4.dist-info/top_level.txt
clinproc-0.2.4.dist-info/RECORD
