Metadata-Version: 2.1
Name: clinproc
Version: 0.2.4
Summary: library for processing clinical trials data from clinicaltrials.gov
Home-page: https://github.com/semajyllek/clinproc
Author: James Kelly
Author-email: mrkellyjam@gmail.com
Classifier: Programming Language :: Python :: 3
Classifier: License :: OSI Approved :: MIT License
Classifier: Operating System :: OS Independent
Requires-Python: >=3.7
License-File: LICENSE
Requires-Dist: lxml
Requires-Dist: spacy (==3.0.1)
Requires-Dist: scispacy
Requires-Dist: negspacy
Requires-Dist: scipy
Requires-Dist: matplotlib
Requires-Dist: pandas
